blaziumpay/__init__.py
blaziumpay/client.py
blaziumpay/errors.py
blaziumpay/types.py
blaziumpay-1.0.0.dist-info/licenses/LICENSE
tests/__init__.py
tests/test_client_validation.py
tests/test_errors.py
tests/test_helpers.py
tests/test_imports.py
tests/test_normalization.py
tests/test_payment_validation.py
tests/test_types.py
tests/test_unverified_webhook.py
tests/test_webhook_verification.py
blaziumpay-1.0.0.dist-info/METADATA
blaziumpay-1.0.0.dist-info/WHEEL
blaziumpay-1.0.0.dist-info/top_level.txt
blaziumpay-1.0.0.dist-info/RECORD
