Metadata-Version: 2.4
Name: blaziumpay
Version: 1.0.0
Summary: Official Python SDK for BlaziumPay - Production-ready crypto payment infrastructure
Home-page: https://github.com/blaziumpay/python-sdk
Author: BlaziumPay
Author-email: BlaziumPay <support@blaziumpay.com>
License: MIT
Project-URL: Homepage, https://blaziumpay.com
Project-URL: Documentation, https://docs.blaziumpay.com
Project-URL: Repository, https://github.com/blaziumpay/python-sdk
Project-URL: Issues, https://github.com/blaziumpay/python-sdk/issues
Keywords: blaziumpay,crypto,payments,blockchain,sdk,ton,solana,bitcoin,web3,cryptocurrency,payment-gateway,python
Classifier: Development Status :: 5 - Production/Stable
Classifier: Intended Audience :: Developers
Classifier: License :: OSI Approved :: MIT License
Classifier: Operating System :: OS Independent
Classifier: Programming Language :: Python :: 3
Classifier: Programming Language :: Python :: 3.8
Classifier: Programming Language :: Python :: 3.9
Classifier: Programming Language :: Python :: 3.10
Classifier: Programming Language :: Python :: 3.11
Classifier: Programming Language :: Python :: 3.12
Classifier: Topic :: Software Development :: Libraries :: Python Modules
Classifier: Topic :: Office/Business :: Financial
Requires-Python: >=3.8
License-File: LICENSE
Requires-Dist: requests>=2.31.0
Provides-Extra: dev
Requires-Dist: pytest>=7.4.0; extra == "dev"
Requires-Dist: pytest-cov>=4.1.0; extra == "dev"
Requires-Dist: black>=23.0.0; extra == "dev"
Requires-Dist: mypy>=1.5.0; extra == "dev"
Requires-Dist: ruff>=0.1.0; extra == "dev"
Dynamic: author
Dynamic: home-page
Dynamic: license-file
Dynamic: requires-python
